lice_tddschn/__init__.py
lice_tddschn/core.py
lice_tddschn/template-afl3.txt
lice_tddschn/template-agpl3-header.txt
lice_tddschn/template-agpl3.txt
lice_tddschn/template-apache-header.txt
lice_tddschn/template-apache.txt
lice_tddschn/template-bsd2.txt
lice_tddschn/template-bsd3.txt
lice_tddschn/template-cc0-header.txt
lice_tddschn/template-cc0.txt
lice_tddschn/template-cc_by-header.txt
lice_tddschn/template-cc_by.txt
lice_tddschn/template-cc_by_nc-header.txt
lice_tddschn/template-cc_by_nc.txt
lice_tddschn/template-cc_by_nc_nd-header.txt
lice_tddschn/template-cc_by_nc_nd.txt
lice_tddschn/template-cc_by_nc_sa-header.txt
lice_tddschn/template-cc_by_nc_sa.txt
lice_tddschn/template-cc_by_nd-header.txt
lice_tddschn/template-cc_by_nd.txt
lice_tddschn/template-cc_by_sa-header.txt
lice_tddschn/template-cc_by_sa.txt
lice_tddschn/template-cddl.txt
lice_tddschn/template-epl.txt
lice_tddschn/template-gpl2-header.txt
lice_tddschn/template-gpl2.txt
lice_tddschn/template-gpl3-header.txt
lice_tddschn/template-gpl3.txt
lice_tddschn/template-isc.txt
lice_tddschn/template-lgpl.txt
lice_tddschn/template-mit.txt
lice_tddschn/template-mpl-header.txt
lice_tddschn/template-mpl.txt
lice_tddschn/template-wtfpl-header.txt
lice_tddschn/template-wtfpl.txt
lice_tddschn/template-zlib.txt
lice_tddschn/tests/__init__.py
lice_tddschn/tests/test_lice.py
lice_tddschn-0.1.5.dist-info/entry_points.txt
lice_tddschn-0.1.5.dist-info/LICENSE
lice_tddschn-0.1.5.dist-info/WHEEL
lice_tddschn-0.1.5.dist-info/METADATA
lice_tddschn-0.1.5.dist-info/RECORD
