Metadata-Version: 2.1
Name: lice-tddschn
Version: 0.1.5
Summary: Generate a license file for a project
Home-page: https://github.com/tddschn/lice-tddschn
License: MIT
Keywords: lice,license,generator
Author: Xinyuan Chen
Author-email: 45612704+tddschn@users.noreply.github.com
Requires-Python: >=3.10,<4.0
Classifier: Development Status :: 4 - Beta
Classifier: Intended Audience :: Developers
Classifier: License :: OSI Approved :: MIT License
Classifier: Operating System :: OS Independent
Classifier: Programming Language :: Python :: 3
Classifier: Programming Language :: Python :: 3.10
Classifier: Topic :: Utilities
Project-URL: Bug Tracker, https://github.com/tddschn/lice-tddschn/issues
Project-URL: Repository, https://github.com/tddschn/lice-tddschn
